waveshare/__init__.py
waveshare_rpi-0.1.3.dist-info/LICENSE
waveshare_rpi-0.1.3.dist-info/METADATA
waveshare_rpi-0.1.3.dist-info/WHEEL
waveshare_rpi-0.1.3.dist-info/top_level.txt
waveshare_rpi-0.1.3.dist-info/RECORD
